{"charging_status": {"country": "United States", "city": "Oceanside", "purpose": "PERSONAL", "power_kw_display": "0.00", "is_purpose_finalized": true, "update_period": 8000, "utility": {"plans": [{"code": "EV-TOU-5-NEM3", "name": "Domestic - Cost-Based, Time of Use, Electric Vehicles (NEM 3.0)", "id": 3436794, "is_ev_plan": true}], "name": "Clean Energy Alliance", "id": 101204}, "lon": -117.3271713256836, "power_kw": 0.0, "session_time": 39172000, "has_charging_receipt": false, "payment_completed": true, "energy_kwh": 29.638901, "total_amount_to_user": 0.0, "device_name": "CP HOME / 214541061163", "api_flag": false, "outlet_number": 1, "state_name": "California", "organization_currency": "USD", "pricing_spec_id": 0, "currency_iso_code": "USD", "current_charging": "done", "lat": 33.246150970458984, "vehicle_info": {"year": 2021, "ev_range": 200, "is_primary_vehicle": true, "model": "XC40 Recharge", "battery_capacity": 78.0, "vehicle_id": 21847141, "make": "Volvo"}, "port_level": 2, "charging_time": 11853000, "device_id": 12048111, "company_id": 12967, "is_home_charger": true, "address1": "Home Charger", "end_time": 1768157570000, "energy_kwh_display": "29.6389", "session_id": 4760273841, "update_data": [{"energy_kwh": 0.0, "power_kw": 0.0, "timestamp": 1768118400000}, {"energy_kwh": 0.0073, "power_kw": 3.1571, "timestamp": 1768118411000}, {"energy_kwh": 0.32913333333333333, "power_kw": 9.143799999999999, "timestamp": 1768118495000}, {"energy_kwh": 2.2201333333333335, "power_kw": 9.072966666666666, "timestamp": 1768119302000}, {"energy_kwh": 4.4738999999999995, "power_kw": 9.068833333333332, "timestamp": 1768120202000}, {"energy_kwh": 6.727933333333333, "power_kw": 9.0654, "timestamp": 1768121101000}, {"energy_kwh": 8.981866666666667, "power_kw": 9.076966666666666, "timestamp": 1768122001000}, {"energy_kwh": 11.2413, "power_kw": 9.085266666666667, "timestamp": 1768122901000}, {"energy_kwh": 13.499966666666666, "power_kw": 9.085366666666665, "timestamp": 1768123802000}, {"energy_kwh": 15.755433666666667, "power_kw": 9.072533333333334, "timestamp": 1768124702000}, {"energy_kwh": 18.010366333333334, "power_kw": 9.079533333333332, "timestamp": 1768125602000}, {"energy_kwh": 20.266033333333336, "power_kw": 9.063966666666666, "timestamp": 1768126502000}, {"energy_kwh": 22.515566333333336, "power_kw": 9.041666666666666, "timestamp": 1768127402000}, {"energy_kwh": 24.762000666666665, "power_kw": 8.977766666666668, "timestamp": 1768128302000}, {"energy_kwh": 26.99936666666667, "power_kw": 9.009966666666665, "timestamp": 1768129202000}, {"energy_kwh": 29.061000333333336, "power_kw": 9.016533333333333, "timestamp": 1768130102000}, {"energy_kwh": 29.4513, "power_kw": 0.0, "timestamp": 1768130702000}, {"energy_kwh": 29.4513, "power_kw": 0.0, "timestamp": 1768131603000}, {"energy_kwh": 29.4513, "power_kw": 0.0, "timestamp": 1768132503000}, {"energy_kwh": 29.4513, "power_kw": 0.0, "timestamp": 1768133403000}, {"energy_kwh": 29.4513, "power_kw": 0.0, "timestamp": 1768134302000}, {"energy_kwh": 29.4513, "power_kw": 0.0, "timestamp": 1768135202000}, {"energy_kwh": 29.4513, "power_kw": 0.0, "timestamp": 1768136103000}, {"energy_kwh": 29.4513, "power_kw": 0.0, "timestamp": 1768137003000}, {"energy_kwh": 29.4513, "power_kw": 0.0, "timestamp": 1768137902000}, {"energy_kwh": 29.4513, "power_kw": 0.0, "timestamp": 1768138802000}, {"energy_kwh": 29.4513, "power_kw": 0.0, "timestamp": 1768139702000}, {"energy_kwh": 29.4513, "power_kw": 0.0, "timestamp": 1768140603000}, {"energy_kwh": 29.4513, "power_kw": 0.0, "timestamp": 1768141503000}, {"energy_kwh": 29.4513, "power_kw": 0.0, "timestamp": 1768142402000}, {"energy_kwh": 29.4513, "power_kw": 0.0, "timestamp": 1768143302000}, {"energy_kwh": 29.4513, "power_kw": 0.0, "timestamp": 1768144202000}, {"energy_kwh": 29.4513, "power_kw": 0.0, "timestamp": 1768145103000}, {"energy_kwh": 29.4513, "power_kw": 0.0, "timestamp": 1768146003000}, {"energy_kwh": 29.4513, "power_kw": 0.0, "timestamp": 1768146902000}, {"energy_kwh": 29.4513, "power_kw": 0.0, "timestamp": 1768147803000}, {"energy_kwh": 29.4513, "power_kw": 0.0, "timestamp": 1768148702000}, {"energy_kwh": 29.4513, "power_kw": 0.0, "timestamp": 1768149602000}, {"energy_kwh": 29.4513, "power_kw": 0.0, "timestamp": 1768150503000}, {"energy_kwh": 29.4513, "power_kw": 0.0, "timestamp": 1768151403000}, {"energy_kwh": 29.4513, "power_kw": 0.0, "timestamp": 1768152302000}, {"energy_kwh": 29.4513, "power_kw": 0.0, "timestamp": 1768152903000}, {"energy_kwh": 29.4513, "power_kw": 0.0, "timestamp": 1768153503000}, {"energy_kwh": 29.4513, "power_kw": 0.0, "timestamp": 1768154103000}, {"energy_kwh": 29.4513, "power_kw": 0.0, "timestamp": 1768154703000}, {"energy_kwh": 29.4513, "power_kw": 0.0, "timestamp": 1768155303000}, {"energy_kwh": 29.4513, "power_kw": 0.0, "timestamp": 1768155903000}, {"energy_kwh": 29.4513, "power_kw": 0.0, "timestamp": 1768156503000}, {"energy_kwh": 29.4513, "power_kw": 0.0, "timestamp": 1768157102000}, {"energy_kwh": 29.638901, "power_kw": 0.0, "timestamp": 1768157570000}, {"energy_kwh": 29.638901, "power_kw": 0.0, "update_date": 1768157596250, "timestamp": 1768157570000}, {"energy_kwh": 29.638901, "power_kw": 0.0, "timestamp": 1768157570000}], "has_utility_info": true, "zipcode": "92058", "last_update_data_timestamp": 1768157570000, "start_time": 1768118400000, "payment_type": "none", "total_amount": 2.84, "billing_time": 1768157572000, "company_name": "CP Home", "start_offset": -28800, "miles_added": 75.99718205128205, "stop_charge_supported": true}}